kitetsu/__init__.py
kitetsu/cli.py
kitetsu/replacesoh_impl.cpython-312-x86_64-linux-gnu.so
kitetsu-0.0.6.dist-info/METADATA
kitetsu-0.0.6.dist-info/WHEEL
kitetsu-0.0.6.dist-info/entry_points.txt
kitetsu-0.0.6.dist-info/top_level.txt
kitetsu-0.0.6.dist-info/RECORD
